[{"msg_id": 186086, "doc_id": 226924, "date": "1876-01-10", "heading": "Telegramme.", "text": "Domesnees, 9. Januar, 9 Uhr Morgens. Heftiger Westwind, Barometer am 8. Januar, 9 Uhr Abends, 29\u201419, an 9. Januar, 9 Uhr Morgens. 29\u20141, Thermometer 2 Grad W\u00e4rme, bew\u00f6lkter Himmel.\nDer Eisstand ist unver\u00e4ndert\nPetersburg, 9. Janua,. (Telegramm des physikalischen Centralobservatorirms an die meteorologische Station des Natursorschervereins zu Riga.) Das Minimum befindet sich heut: aus dem Bottnischen Meerbusen. Aus dem Baltischem Meere weht heftiger S\u00fcdwestwind. ftellweise begleitet von Regen. Aus\n\n\tdem  weht schwacher Westwind. Die Witterung ist fast in ganz Nordwestru\u00dfland unbest\u00e4ndig.\nBarometer Thermometer um 7 Uhr Morgen?.\nUleaborg 737 Mill. \u201413 Grad C.\nArchangel. ... 746 \u201e \u201413\nPetersburg 740 .. +2\nReval 742 ~ + 2 .\nWilna 750 \u201e +1\nWarschau. ... 761 \u201e \u2014 4\nKiew 762 ~ \u2014 1\nOdessa 768 \u201e \u2014 3\n(Riga) 743 . +2\n"}, {"msg_id": 191377, "doc_id": 232257, "date": "1877-01-03", "heading": "Telegramme.", "text": "\tDomeSneeS, 2. Januar. S I Uhr Morgens, M\u00e4\u00dfiger S\u00fcdostwind, Barometer am t. Januar, 8 Uhr Abends, 29-85. am 2. Januar., 8 Uhr Morgen\u00ab, 29 \u2014 80, Thermometer 5 Grad K\u00e4lte, bew\u00f6lkter Himmel. \u2014 Der EiSstimd ist unver\u00e4ndert.\nPetersburg, St. December. (Telegramm de\u00ab physikalischen Centralobservatorium\u00ab an die meteorologische Station des Ratursorscherverein\u00ab zu Riga.) Ein barometrisches Minimum \u00e4u\u00dfert sich in Central-Europa. Auf dem s\u00fcdlichen Theile des Baltischen Meeres wird der Ostwind wahrscheinlich bedeutend heftiger werden. Aus dem Schwarzen Meere weht m\u00e4\u00dfiger S\u00fcdwestwind.\nVtumttti Thermometer um 7 Uhr MorqenS.\nUleabvrg 763 Mill. \u201415 Grad \u00ab.\nArchangelsk ... 759 . \u201414\nPetersburg 769 . \u201415\nMoskau 771 . \u201414\nLibau 765 . \u2014 8\nKiew 757 . \u2014 2 .\nSaratow 764 . \u201410\n(Riga) . ~ 765 . \u20141"}, {"msg_id": 186666, "doc_id": 227532, "date": "1876-02-19", "heading": "Telegramme.", "text": "Domesnees, 18. Februa. 9 Uh, Morgens, M\u00e4\u00dfiger Ostwiud, Barometei am 17. Februar,\n9 Uhr Abends, 29\u201444, an] 18. Februar. 9 Uhr\nMorgens. 29\u201438. Thermoteter 3 Grad Frost, bew\u00f6lkter Himmel. i\n\u2014 Der Eisstand ist unver\u00e4itcrt.\nPetersburg, 18. Febrt\u00bbr. (Telegramm des physikalischen Centralobservatomms an die meteoro-\n\n\tlogische Station des Naturforschervereins zu Riga.j Das bei Wilna befindlich gewesene Minimum nimmt seine Richtung nach dem S\u00fcden Ru\u00dflands, begleitet von schwachem Winde und Regen. Ein neues Miuimum \u00e4u\u00dfert sich auf der Ostsee. Auf dem Baltischen Meere weht schwacher Ostwind.\nBarometer Thermometer um 7 Uhr Morgens.\nUleaborg 767 Mill. \u201418 Grad C.\nArchangel. ... 772 . \u201420\nPetersburg 765 , \u201417\nWilna.. 758 . +1\nKiew 755 \u201e 0\nMoskau 764 \u201e \u2014 4\nCharkow 759 \u201e \u2014 1\nKasan 767 . \u2014 9\n(Riga) 755 . \u2014 2\n"}, {"msg_id": 178918, "doc_id": 217870, "date": "1874-05-15", "heading": "Telegramme.", "text": "DomeSneeS, 14. Mai. 8 Uhr Morg. Schwacher Nordwind, Barometer am 13. Mai. 8 Uhr Aod\u00ab., 29\u201448. am 14. Mai. 8 Uhr Morgen\u00ab. 29\u2014-S2, Thermometer 6 Grad W\u00e4rme, heiterer Himmel.\n"}, {"msg_id": 175840, "doc_id": 215136, "date": "1873-10-17", "heading": "Telegramme.", "text": "DomeSnees, 16. October. 9 Uhr Morg. M\u00e4\u00dfiger Nordwestwind. Barometer am 15. Octbr.. 8 Uhr Add\u00ab.. 29\u201457. am 16 October. 8 Uhr Morgen\u00ab. 29\u201468. Thermometer 5 Grad W\u00e4rme; heiterer Himmel.\n\n\tPetersburg, t 6. October. (Telegramm dt\u00ab Physikalifchen Centralobservatorium\u00ab an die meteorologische Station de\u00ab Naturforscherverein\u00ab zu Riga.) Der atmosph\u00e4rische Druck befindet sich im ganzen Reiche \u00fcber der Normalh\u00f6he. Da\u00ab Wetter ist \u00fcberall warm und regnerisch, mit Ausnahme der \u00f6stlichen Gouverntment\u00ab. Der Wind weht schwach au\u00ab Nordwesten. Im Osten Ru\u00dfland\u00ab herrscht West- und S\u00fcdwestwind.\nBarometer Thermometer um 7 Uhr Morgens.\nArchangel \u2014 Mill. \u2014 Grad C.\nJekaterinenburg 749 \u201e + 3 .\nKiew 750 . + 7 .\nReval 764 . + 5 .\nMo\u00abkau 751 . + 4 (?) .\nOdessa 762 . -f 11\n(Riga) 766 . +5\n"}, {"msg_id": 190526, "doc_id": 231356, "date": "1876-11-04", "heading": "Telegramme.", "text": "\tDomeSneeS, 3. November, 9 Uhr Morgens. M\u00e4\u00dfiger Nordwind, Barometer am 2. November, 8 Uhr Abends, 29\u201449, am 3. November. 8 Uhr Morgen\u00ab. 29 \u2014 53, Thermometer 1 Grad W\u00e4rme, bew\u00f6lkter Himmel.\n"}, {"msg_id": 168127, "doc_id": 205697, "date": "1871-12-16", "heading": "Telegramme.", "text": "Domesnees, 15. December, 9 Uhr Vorm. M\u00e4\u00dfiger Westwind, Barometer am 14. December, 8 Uhr AbendS. 29\u201423, am 15 December, 8 Uhr Morgens, 29\u201425, Thermometer 2 Grad Warme, bew\u00f6lkter Himmel.\n"}, {"msg_id": 167067, "doc_id": 204532, "date": "1871-10-04", "heading": "Telegramme.", "text": "Domesnees, 2. October. 9 Uhr Vorm. Schwacher Westwind, Barometer am 1. October. Abends 8 Udr, 29\u201459. am 2. October, Morgens 8 Uhr, 29\u201463. Thermometer 6 Grad W\u00e4rme, bew\u00f6lkter Himmel.\n"}, {"msg_id": 196386, "doc_id": 238118, "date": "1877-12-12", "heading": "Nichtofficielle Telegramme.", "text": "Domesnees, 11. December, 9 Uhr Morg. Starker S\u00fcdwind. Barometer am 10. December, 8 Uhr Abends. 29\u201454, am 11. December, 8 Uhr Morgen\u00ab. 29\u201425 , Thermometer 7 Grad K\u00e4lte, bew\u00f6lkter Himmel.\nSturmwarnungs.Telegramm. "}, {"msg_id": 170435, "doc_id": 208734, "date": "1872-07-11", "heading": "Telegramme.", "text": "Domesnees. 10. Juli. 9 Uhr Vormittag\u00ab. M\u00e4\u00dfiger Rordostwlnd. Barometer am 9. Juli, 8 Uhr Abend\u00ab 29\u201460. a\u00ab 10. Juli. 8 Uhr Morgen\u00ab. 29-63, Thermomeler 14 Grad W\u00e4rme, bew\u00f6lkter Himmel.\n"}, {"msg_id": 167717, "doc_id": 205221, "date": "1871-11-17", "heading": "Telegramme.", "text": "Domesnees, 16. November, 9 Uhr Vorm. M\u00e4\u00dfiger Noroostwind, Barometer am 15. November, 8 Uhr Abend\u00bb. 29\u201458, am 16 November, 8 Uhr Morgen\u00ab, 29\u201458, Thermometer 0 Grad, bew\u00f6lkter Himmel.\n"}, {"msg_id": 174261, "doc_id": 213817, "date": "1873-07-09", "heading": "Telegramme.", "text": "Domcsnees, 8. Juli, 8 Uhr Morgens. Schwacher Westwind. Barometer am 7. Juli. 8 Uhr Abends. 29\u201436, am 8. Juli. 8 Uhr Morgens. 29\u201432, Thermometer 14 Grad W\u00e4rme; bew\u00f6lkter Himmel.\n"}, {"msg_id": 174596, "doc_id": 214176, "date": "1873-08-04", "heading": "Telegramme.", "text": "Domesnees, 3. August, 8 Uhr Morgens. Schwacher Westwind. Barometer am 2. August. 8 Uhr Abend\u00ab. 29\u201426. am 3. August. 8 Uhr Morgen\u00bb. 29\u201430. Thermometer 12 Grad Warme: bew\u00f6lkter Himmel.\n"}, {"msg_id": 187772, "doc_id": 228708, "date": "1876-05-07", "heading": "Telegramme.", "text": "Domesnees, 6. Mai, 9 \u00dcb, Morgen\u00ab. M\u00e4\u00dfiger Nordwind, Barometer am 5. Mai, 9 Uhr Abends. 29 \u2014 48, am 6. Mai. 9 Uhr Morgens, 29 \u2014 53, Thermometer 2 Grad W\u00e4rme, heiterer Himmel.\n"}, {"msg_id": 167729, "doc_id": 205237, "date": "1871-11-18", "heading": "Telegramme.", "text": "Domesnees, 17 November, 9 Uhr Vorm. M\u00e4\u00dfiger S\u00fcdwestwind, Barometer am 16. November, 8 Uhr Abend\u00bb, 29\u201452. am 17. November. 8 Uhr Morgens, 29\u201446, Thermometer 0 Grad, bew\u00f6lkter Himmel.\n"}, {"msg_id": 168104, "doc_id": 205663, "date": "1871-12-14", "heading": "Telegramme.", "text": "Domesnces. 13. December, 9 Uhr Vorm. M\u00e4\u00dfiger S\u00fcdwestwind, Barometer am 12. December, 8 Uhr Abend\u00ab, 29\u201435, am 13. December. 8 Uhr Morgen\u00ab. 29\u201439, Thermometer 2 Grad W\u00e4rme, bew\u00f6lkter Himmel.\n"}, {"msg_id": 179633, "doc_id": 218746, "date": "1874-07-19", "heading": "Telegramme.", "text": "DomeSneeS, 18. Juli. 9 Uhr Morg. Schwacher Ostwind. Barometer am 17. Juli. 8 \u00dcbr AbdS.. 29\u201449. am 18. Juli. 8 Uhr Morgen\u00ab. 29\u201448. Thermometer 15 Gr.'d W\u00e4rme, heiterer Himmel\n\n\tPetersburg, 18. luli. \u00abTelegramm des Physikatischen EentralobservatoriumS an die meteorologische Station dcS RaturforschervereinS zu Riga.) DaS Barometer f\u00e4llt allmalich in Skandinavien und am Baltischen Meere. Der Wind ist nach S\u00fcden umgesprungen. Im Westen deS Reiche\u00bb ist der Himmel heiter; im Osten fallt anhaltender Regen. Zn Centrairu\u00dfland weht m\u00e4\u00dfiger Nordwestwind.\nBarometer Thermometer um 7 Uhr Morgen\u00ab.\nArchangel \u2014 Mill. \u2014 \u00abKrad E.\nUleaborg 761 . +19\nKuopio 762 . +17\nPetersburg 763 . +15 .\nWindau 758 \u00ec +20\nWilna 761 ] +17\nWarschau 757 . +20\nKiew 761 . +16\nOdessa 759 . +21\nCharkow 756 . +16\nMo\u00abkau 759 . +9\nKasan 752 l +12\nOrenburg .... 756 . +19\n\u00abRiga) 761 . +15\n"}, {"msg_id": 167157, "doc_id": 204609, "date": "1871-10-08", "heading": "Telegramme.", "text": "Domesnees, 7. October, 9 Uhr Vorm. M\u00e4\u00dfiger Westwind, Barometer am 6. October. AbendS 8 Uhr. 29\u201465. am 7. October. MorgenS 8 Uhr, 29-60, Thermometer 6 Grad W\u00e4rme, bew\u00f6lkter Himmel.\n"}, {"msg_id": 167396, "doc_id": 204866, "date": "1871-10-25", "heading": "Telegramme.", "text": "Domesnees, 23. October. 9 Uhr Vorm. Starker Nordwestwind, Barometer am 22. October. Abends 8 Uhr. 29\u201424. am 23. October. Morgens 8 \u00dcbr, 29\u201426. Thermometer l Grad W\u00e4rme, bew\u00f6lkter Himmel.\n"}, {"msg_id": 168188, "doc_id": 205796, "date": "1871-12-22", "heading": "Telegramme.", "text": "DomeSnees, 21. December, 9 Uhr Vorm. Starker  Barometer am 20. December, 8 Uhr Abends, 29\u201462, am 21. December. 8 Uhr Morgen\u00ab, 29\u201472. Thermometer 1 Grad W\u00e4rme, klarer Himmel.\n"}]